kimmy/OneZone.py
kimmy/__init__.py
kimmy-0.1.dist-info/LICENSE
kimmy-0.1.dist-info/METADATA
kimmy-0.1.dist-info/WHEEL
kimmy-0.1.dist-info/top_level.txt
kimmy-0.1.dist-info/RECORD
