Metadata-Version: 2.1
Name: kimmy
Version: 0.1
Summary: Chemical evolution in galaxies
Home-page: http://github.com/jobovy/kimmy
Author: Jo Bovy
Author-email: bovy@astro.utoronto.ca
License: MIT
Platform: UNKNOWN
Requires-Dist: numpy
Requires-Dist: astropy
